slizaiupload/__init__.py
slizaiupload/config.py
slizaiupload/datatypes.py
slizaiupload/helpers.py
slizaiupload/main.py
slizaiupload/upload.py
slizaiupload/uploader_service.py
slizaiupload-1.2.4.dist-info/entry_points.txt
slizaiupload-1.2.4.dist-info/LICENSE
slizaiupload-1.2.4.dist-info/METADATA
slizaiupload-1.2.4.dist-info/WHEEL
slizaiupload-1.2.4.dist-info/RECORD
